agent_config.yaml
siada/__init__.py
siada/agent_hub/__init__.py
siada/agent_hub/coder/browser_agent.py
siada/agent_hub/coder/bug_fix_agent.py
siada/agent_hub/coder/card_agent.py
siada/agent_hub/coder/code_gen_agent.py
siada/agent_hub/coder/fe_gen_agent.py
siada/agent_hub/coder/issue_review_agent.py
siada/agent_hub/coder/prompt/__init__.py
siada/agent_hub/coder/prompt/base/__init__.py
siada/agent_hub/coder/prompt/base/capabilities.py
siada/agent_hub/coder/prompt/base/non_interactive.py
siada/agent_hub/coder/prompt/base/prompt_builder.py
siada/agent_hub/coder/prompt/base/rules.py
siada/agent_hub/coder/prompt/base/tool_use.py
siada/agent_hub/coder/prompt/bug_prompt/bug_fix_prompt.py
siada/agent_hub/coder/prompt/bug_prompt/rules.py
siada/agent_hub/coder/prompt/card_prompt/__init__.py
siada/agent_hub/coder/prompt/card_prompt/card_prompt.py
siada/agent_hub/coder/prompt/card_prompt/rules.py
siada/agent_hub/coder/prompt/card_prompt.py
siada/agent_hub/coder/prompt/code_gen_prompt.py
siada/agent_hub/coder/prompt/compact_prompt.py
siada/agent_hub/coder/prompt/fe_gen_prompt.py
siada/agent_hub/coder/prompt/issue_review_prompt.py
siada/agent_hub/coder/select_agent.py
siada/agent_hub/coder/tracing/__init__.py
siada/agent_hub/coder/tracing/bug_fix_trace_collector.py
siada/agent_hub/coder/tracing/logger_tracing_processor.py
siada/agent_hub/context_filter/__init__.py
siada/agent_hub/context_filter/api_message_transfer_filter.py
siada/agent_hub/context_filter/base_filter.py
siada/agent_hub/context_filter/context_capture_filter.py
siada/agent_hub/context_filter/message_history_capture_filter.py
siada/agent_hub/context_filter/utils.py
siada/agent_hub/hooks/__init__.py
siada/agent_hub/hooks/agent_processors/__init__.py
siada/agent_hub/hooks/agent_processors/context_track_processor.py
siada/agent_hub/hooks/context_capture_filter.py
siada/agent_hub/hooks/io_hooks.py
siada/agent_hub/hooks/processors/__init__.py
siada/agent_hub/hooks/processors/checkpointing_processor.py
siada_cli-1.5.6.dist-info/METADATA
siada_cli-1.5.6.dist-info/WHEEL
siada_cli-1.5.6.dist-info/entry_points.txt
siada_cli-1.5.6.dist-info/licenses/LICENSE
siada_cli-1.5.6.dist-info/RECORD
