Metadata-Version: 2.4
Name: siada-cli
Version: 1.5.6
Summary: Siada CLI is a Ai Pair Programming Tool in terminal
License: Apache-2.0
License-File: LICENSE
Requires-Python: >=3.12,<4.0
Classifier: Environment :: Console
Classifier: Intended Audience :: Developers
Classifier: License :: OSI Approved :: Apache Software License
Classifier: Programming Language :: Python
Classifier: Programming Language :: Python :: 3
Classifier: Programming Language :: Python :: 3.12
Classifier: Programming Language :: Python :: 3.13
Classifier: Programming Language :: Python :: 3.14
Classifier: Topic :: Software Development
Requires-Dist: aiohttp (>=3.8.0,<4.0.0)
Requires-Dist: binaryornot (==0.4.4)
Requires-Dist: browsergym (>=0.14.2,<0.15.0)
Requires-Dist: click (>=8.2.1,<9.0.0)
Requires-Dist: configargparse (>=1.7,<2.0.0)
Requires-Dist: diskcache (==5.6.3)
Requires-Dist: drawille (>=0.1.0,<1.0.0)
Requires-Dist: fastapi (>=0.110.0,<1.0.0)
Requires-Dist: gitpython (>=3.1.0,<4.0.0)
Requires-Dist: grep-ast (>=0.9.0,<1.0.0)
Requires-Dist: gymnasium (>=1.2.0,<2.0.0)
Requires-Dist: litellm (>=1.72.6,<2.0.0)
Requires-Dist: mcp (>=1.0.0,<2.0.0)
Requires-Dist: networkx (>=3.5.0,<4.0.0)
Requires-Dist: numpy (>=1.24.0,<2.0.0)
Requires-Dist: openai (>=1.102.0,<2.0.0)
Requires-Dist: openai-agents (==0.3.2)
Requires-Dist: openhands-aci (==0.3.0)
Requires-Dist: pandas (>=2.0.0,<3.0.0)
Requires-Dist: partial-json-parser (>=0.2.1.1.post6,<1.0.0)
Requires-Dist: patch-ng (>=1.18.1,<2.0.0)
Requires-Dist: pathspec (>=0.12.0,<1.0.0)
Requires-Dist: pexpect (>=4.9.0,<5.0.0)
Requires-Dist: playwright (>=1.40.0,<2.0.0)
Requires-Dist: prompt-toolkit (>=3.0.51,<4.0.0)
Requires-Dist: psutil (>=7.0.0,<8.0.0)
Requires-Dist: pydantic (>=2.6.0,<3.0.0)
Requires-Dist: pydantic-settings (>=2.2.0,<3.0.0)
Requires-Dist: pygments (>=2.19.1,<3.0.0)
Requires-Dist: rich (>=13.0.0,<=14.1.0)
Requires-Dist: scikit-learn (>=1.3.0,<2.0.0)
Requires-Dist: shtab (>=1.7,<2.0.0)
Requires-Dist: termcolor (>=3.1.0,<4.0.0)
Requires-Dist: tqdm (>=4.67.1,<5.0.0)
Requires-Dist: trafilatura (>=2.0.0,<3.0.0)
Requires-Dist: uvicorn (>=0.27.0,<1.0.0)
